Maquina de estados/RegSerieCargaParalela_EN.sv
// Para registro Q

// Register Q: mantiene el multiplicador y hace corrimientos hacia la derecha

// Características:
// Entrada paralela - salida serie - Corrimiento derecha - EN


`timescale 1ns/1ps 

module RegSerieCargaParalela_EN #(parameter BITS=8) (
	input clk, rst, LS, EN, D, 
  	//D va a ser cero para reg
  	input [BITS-1:0] DP,
  	output reg out
);
  
  //LS --> load/shift: Carga con 0, corrimiento con 1
  //EN --> enable: no hace nada con 0, funciona con 1 
  
  reg [BITS-1:0] state, next_state;
  
  //Memoria
  always @ (posedge clk) begin 
    if (!rst) state <= 0; 
    else state <= next_state;
  end
  
  //Siguiente estado
  always @ (*) begin
    //Funciona
    if(EN == 1) begin
        // Cargar datos de DP
        if (LS == 0) next_state = DP;

        // Hacer corrimiento derecha
        else next_state = {D, state[BITS-1:1]};
    end
    //No hace nada
    else next_state = state;
  end
  
  //Salida
  always @ (*) begin
    out = state[0];
  end
  
endmodule

Maquina de estados/Contador.sv
// Contador hacia abajo con enable

`timescale 1ns/1ps

module ContadorAbajo_EN #(parameter BITS=3)(
	input clk, rst, EN,
  	output reg [BITS-1:0] cuenta
);

  reg [BITS-1:0] state, next_state;
  
  //Memoria
  always @ (posedge clk) begin
    if (!rst) state <= 7;
	else state <= next_state;
  end
  
  //Lógica Siguiente Estado
  always @ (*) begin
    if (EN == 0) begin //No seguir contando
        next_state = state;
    end
    else begin //Seguir contando
        next_state = state-1;
    end
  end
  
  //Lógica Salida
  always @ (*) begin
    cuenta = state;
  end  
  
endmodule

Maquina de estados/Sumador.sv
//================  Sumador de n bits ================//


`timescale 1ns/1ps

module sumador #(parameter BITS=8)(
  input [BITS-1:0] A, B, 
  input Cin, 
  output reg [BITS-1:0] S, 
  output reg Cout
);
  
  always @ (*) begin
    {Cout,S} = A+B+Cin;
  end
  
endmodule

Maquina de estados/RegSalidaSerieYParalela_EN.sv
// Para registro A

// Register A: mantiene la suma parcial con el multiplicando y hace corrimientos hacia la derecha

// Características:
// Entrada paralela - salida serie y paralela - Corrimiento derecha - EN


`timescale 1ns/1ps 

module RegSalidaSerieYParalela_EN #(parameter BITS=8) (
	input clk, rst, LS, EN, D, 
  	//D va a ser cero para reg
  	input [BITS-1:0] DP,
  	output reg outSerie,
 	output reg [BITS-1:0] outParalela
);
  
  //LS --> load/shift: Carga con 0, corrimiento con 1
  //EN --> enable: no hace nada con 0, funciona con 1 
  
  reg [BITS-1:0] state, next_state;
  
  //Memoria
  always @ (posedge clk) begin 
    if (!rst) state <= 0; 
    else state <= next_state;
  end
  
  //Siguiente estado
  always @ (*) begin
    //Funciona
    if(EN == 1) begin
      if (BITS == 1) begin
        // Cargar datos de DP
        if (LS == 0) next_state = DP;
        // Hacer corrimiento derecha
        else next_state = D;
      end
      else begin     
        // Cargar datos de DP
        if (LS == 0) next_state = DP;
        // Hacer corrimiento derecha
        else next_state = {D, state[BITS-1:1]};
      end 
        
    end
    //No hace nada
    else next_state = state;
  end
  
  //Salida
  always @ (*) begin
    outSerie = state[0];
    outParalela = state;
  end
  
endmodule

Maquina de estados/RegParalelaParalela_EN.sv
// Para registro B
// Register B: mantiene el multiplicando

// Características:
// Entrada paralela - salida paralela - EN


`timescale 1ns/1ps 

module RegParalelaParalela_EN #(parameter BITS=8) (
	input clk, rst, EN, 
  	input [BITS-1:0] DP,
  	output reg [BITS-1:0] out
);
  
  //EN --> enable: no hace nada con 0, funciona con 1 
  
  reg [BITS-1:0] state, next_state;
  
  //Memoria
  always @ (posedge clk) begin 
    if (!rst) state <= 0; 
    else state <= next_state;
  end
  
  //Siguiente estado
  always @ (*) begin
    //Funciona
    if(EN == 1) next_state = DP;
    //No hace nada
    else next_state = state;
  end
  
  //Salida
  always @ (*) begin
    out = state;
  end
  
endmodule

Maquina de estados/Base.sv

`include "RegSerieCargaParalela_EN.sv"
`include "RegParalelaParalela_EN.sv"
`include "RegSalidaSerieYParalela_EN.sv"
`include "Contador.sv"
`include "Sumador.sv"

`timescale 1ns/1ps

module TOP #(parameter BITS=8)(
  	input Load_Regs, Shift_Regs, Add_Regs, Decr_P,
  	input clk, rst,
	input [BITS-1:0] DP_B, DP_Q, //DP_B: multiplicando, DP_Q: multiplicador
  output reg [2*BITS:0] Producto,
  	output reg Q0, Zero,
  output reg [2:0] P
  	
  	//Zero es 1 si el contador llegó a cero
  	//Zero es 0 si el contador no ha llegado a cero
);
  
  wire [BITS-1:0] salidaRegB, salidaParalelaA, salidaParalelaQ, resultadoSum;
  wire salidaSerieA, salidaSerieQ, salidaSerieC, salidaParalelaC, cout;
  wire [2:0] cuenta;
  reg LS_A, LS_Q, EN_A, EN_C, EN_Q;
  
  //Registro B
  RegParalelaParalela_EN #(.BITS(BITS)) RegisterB (.clk(clk), 
                                      .rst(rst), 
                                      .EN(Load_Regs),
                                      .DP(DP_B), 
                                      .out(salidaRegB));
  
  //Registro C
  RegSalidaSerieYParalela_EN #(.BITS(1)) RegisterC (.clk(clk), 
                                      .rst(rst),
                                      .LS(Shift_Regs),
                                   	  .EN(EN_C),
                                      .D(0),
                                      .DP(cout),                                                .outSerie(salidaSerieC),                                      .outParalela(salidaParalelaC));
  
  //Registro A
  RegSalidaSerieYParalela_EN #(.BITS(BITS)) RegisterA (.clk(clk), 
                                      .rst(rst), 
                                      .LS(LS_A),
                                      .EN(EN_A),
                                      .D(salidaSerieC),
                                      .DP(resultadoSum), 
                                      .outSerie(salidaSerieA),                                      .outParalela(salidaParalelaA));
  
  //Registro Q
  RegSalidaSerieYParalela_EN #(.BITS(BITS)) RegisterQ (.clk(clk), 
                                      .rst(rst), 
                                      .LS(LS_Q),
                                      .EN(EN_Q),   
                                      .D(salidaSerieA),
                                      .DP(DP_Q),
                                      .outSerie(salidaSerieQ),                                      .outParalela(salidaParalelaQ));

  
  sumador #(.BITS(BITS)) sum (.A(salidaParalelaA),
                               .B(salidaRegB),
                              .Cin(salidaSerieC),
                               .S(resultadoSum),
                               .Cout(cout));
  
  
  ContadorAbajo_EN #(.BITS(3)) RegisterP (.clk(clk), 
                              .rst(rst), 
                              .EN(Decr_P),
                              .cuenta(cuenta));
  
  
  //VERIFICAR CONDICIONES QUE VIENEN DEL CONTROLADOR
  always @ (*) begin
    if (Load_Regs == 1) begin
    	//EN_B = 1; //B en modo carga
      	EN_Q = 1;
      	LS_Q = 0; //Q en modo carga
    end
    else begin
        //EN_B = 0; //B en modo hold
        LS_Q = 1; //Q en modo contar
      	EN_Q = 0;
    end
  end
  
  always @ (*) begin
    if (Add_Regs == 1) begin
    	EN_A = 1;	
      	LS_A = 0;
    end
    else begin
       LS_A = 1;
       EN_A = 0;	
    end
    
  end
  
  always @ (*) begin
    if (Shift_Regs == 1) begin
    	EN_C = 1;
      	EN_A = 1;
      	EN_Q = 1;
      	LS_A = 1;
      	LS_Q = 1;
    end
    else begin
       	LS_A = 1;
     	EN_C = 0;
      	EN_A = 0;
      	EN_Q = 0;
     	//LS_A = 0;
      	//LS_Q = 0;
    end
    
  end
  
  // SALIDAS
  always @ (*) begin
    
    Producto = {salidaSerieC, salidaParalelaA, salidaParalelaQ};
    Q0 = salidaSerieQ;
    P = cuenta;
    
    if(cuenta == 0) begin
    	Zero = 1;
    end
    else Zero = 0;
    
  end

  
  
endmodule

Maquina de estados/Maq_estados.sv
`timescale 1ns/1ps

module GeneradorMoore(
input clk, rst,pulso,
input  zero,
output reg [2:0] salida);

reg [2:0] state,next_state;


parameter Load=3'b000,Shift=3'b001, Add=3'b010,Decr=3'b011,Ready=3'b100;
  
always@ (posedge clk) begin
  if(!rst) state<=Ready;
	else state<=next_state;
end

always@ (*) begin
 
	case(state)
	Load:begin
		if(pulso==0) next_state= Shift;
		else next_state=Add;
		end
	Shift:begin 
      if(pulso==0) next_state= Decr;
		else next_state=3'b011;
		end
	Add:begin 
      if(pulso==0) next_state= Shift;
		else next_state=Shift;
		end
	Decr:begin 
      if((pulso==0) && (zero==1'b1)) next_state= Ready ;
		else next_state= Load ;
		end
    Ready:begin
      	next_state= Ready ;
    end
    default:next_state= Load; 
      
	endcase
  salida=state;
end
endmodule

Maquina de estados/design.sv
`include "Base.sv"
`include "Maq_estados.sv"
`timescale 1ns/1ps
module General(
input clk, rst, q,Zero,
input [7:0] DP_B, DP_Q, //DP_B: multiplicando, DP_Q: multiplicador
  output reg [16:0] Producto,
  output reg [2:0] ready);
  
  wire Q0, zero;
  wire [2:0] cuenta;
  wire [2:0] salida_estados;
  reg Load_Regs, Shift_Regs, Add_Regs, Decr_P;
  
  parameter Load=3'b000,Shift=3'b001, Add=3'b010,Decr=3'b011,Ready=3'b100;
  
  
  GeneradorMoore FSM(.clk(clk),.rst(rst),.pulso(q), .zero(Zero),.salida(salida_estados));
  
TOP #(.BITS(8)) DUT (.Load_Regs(Load_Regs),
                          .Shift_Regs(Shift_Regs), 
                          .Add_Regs(Add_Regs), 
                          .Decr_P(Decr_P), 
                         .clk(clk), 
                          .rst(rst),         
                          .DP_B(DP_B), 
                          .DP_Q(DP_Q),
                          .Producto(Producto),
                          .Q0(Q0),
                      .Zero(zero),
                         .P(cuenta));  
  


  always @ (*) begin
    ready = salida_estados;
    case(salida_estados)
	Load:begin
		Load_Regs =1;
      	Shift_Regs =0;
      	Add_Regs =0;
      	Decr_P=0;
		end
	Shift:begin 
      	Load_Regs =0;
      	Shift_Regs =1;
      	Add_Regs =0;
      	Decr_P=0;
		end
	Add:begin 
      Load_Regs =0;
      	Shift_Regs =0;
      	Add_Regs =1;
      	Decr_P=0;
		end
	Decr:begin 
      Load_Regs =0;
      	Shift_Regs =0;
      	Add_Regs =0;
      	Decr_P=1;
		end
    default:
      begin
        Load_Regs =1;
      	Shift_Regs =0;
      	Add_Regs =0;
      	Decr_P=0;
      end
	endcase
  
  
  end

endmodule

Maquina de estados/testbench.sv
// Code your testbench here
// or browse Examples

//`include "Maq_estados.sv"
`timescale 1ns/1ps



module testbench;
  
  
  reg clk,rst,q,zero;
  reg  [2:0] salida_estados;
  reg  [7:0] multiplicador, multiplicando;
  wire [2:0] ready;
  wire [16:0] producto;

  General Estados(.clk(clk),
                  .rst(rst),
                  .DP_B(multiplicador),
                  .DP_Q(multiplicando),
                  .ready(ready),
                  .Producto(producto));
  
//  GeneradorMoore FSM(.clk(clk),.rst(rst),.pulso(q), .zero(zero),.salida(ready));  
  
initial begin
        $dumpfile("testbench.vcd");
        $dumpvars(0,testbench);
  end
  
  initial begin
    clk = 0;
  end
  
  always begin
    #5 clk = ~clk;
  end
  
  initial begin
    rst<=0;
    @(posedge clk) 
    rst<=1;
    multiplicador = 8'b00010111;
    multiplicando = 8'b00010001;
    
    //while(ready != 3'b100) begin
      //@(posedge clk);
    
  	//end
    
    repeat(50)begin
      @(posedge clk);
    end

    $finish;
  end
  
  
  
  initial begin
    
    $monitor("ready=%b, producto=%b", ready, producto);
  end


    
endmodule

Maquina de estados/testbench.vcd
$date
	Thu Nov 11 19:24:13 2021
$end
$version
	Icarus Verilog
$end
$timescale
	1ps
$end
$scope module testbench $end
$var wire 3 ! ready [2:0] $end
$var wire 17 " producto [16:0] $end
$var reg 1 # clk $end
$var reg 8 $ multiplicador [7:0] $end
$var reg 8 % multiplicando [7:0] $end
$var reg 1 & rst $end
$var reg 1 ' zero $end
$scope module Estados $end
$var wire 8 ( DP_B [7:0] $end
$var wire 8 ) DP_Q [7:0] $end
$var wire 1 ' Zero $end
$var wire 1 # clk $end
$var wire 1 # q $end
$var wire 1 & rst $end
$var wire 1 * zero $end
$var wire 3 + salida_estados [2:0] $end
$var wire 3 , cuenta [2:0] $end
$var wire 1 - Q0 $end
$var wire 17 . Producto [16:0] $end
$var reg 1 / Add_Regs $end
$var reg 1 0 Decr_P $end
$var reg 1 1 Load_Regs $end
$var reg 1 2 Shift_Regs $end
$var reg 3 3 ready [2:0] $end
$scope module DUT $end
$var wire 1 / Add_Regs $end
$var wire 8 4 DP_B [7:0] $end
$var wire 8 5 DP_Q [7:0] $end
$var wire 1 0 Decr_P $end
$var wire 1 1 Load_Regs $end
$var wire 1 2 Shift_Regs $end
$var wire 1 # clk $end
$var wire 1 & rst $end
$var wire 1 6 salidaSerieQ $end
$var wire 1 7 salidaSerieC $end
$var wire 1 8 salidaSerieA $end
$var wire 8 9 salidaRegB [7:0] $end
$var wire 8 : salidaParalelaQ [7:0] $end
$var wire 1 ; salidaParalelaC $end
$var wire 8 < salidaParalelaA [7:0] $end
$var wire 8 = resultadoSum [7:0] $end
$var wire 3 > cuenta [2:0] $end
$var wire 1 ? cout $end
$var reg 1 @ EN_A $end
$var reg 1 A EN_C $end
$var reg 1 B EN_Q $end
$var reg 1 C LS_A $end
$var reg 1 D LS_Q $end
$var reg 3 E P [2:0] $end
$var reg 17 F Producto [16:0] $end
$var reg 1 - Q0 $end
$var reg 1 * Zero $end
$scope module RegisterA $end
$var wire 1 @ EN $end
$var wire 1 C LS $end
$var wire 1 # clk $end
$var wire 1 & rst $end
$var wire 8 G DP [7:0] $end
$var wire 1 7 D $end
$var reg 8 H next_state [7:0] $end
$var reg 8 I outParalela [7:0] $end
$var reg 1 8 outSerie $end
$var reg 8 J state [7:0] $end
$upscope $end
$scope module RegisterB $end
$var wire 8 K DP [7:0] $end
$var wire 1 1 EN $end
$var wire 1 # clk $end
$var wire 1 & rst $end
$var reg 8 L next_state [7:0] $end
$var reg 8 M out [7:0] $end
$var reg 8 N state [7:0] $end
$upscope $end
$scope module RegisterC $end
$var wire 1 O D $end
$var wire 1 A EN $end
$var wire 1 2 LS $end
$var wire 1 # clk $end
$var wire 1 & rst $end
$var wire 1 ? DP $end
$var reg 1 P next_state $end
$var reg 1 ; outParalela $end
$var reg 1 7 outSerie $end
$var reg 1 Q state $end
$upscope $end
$scope module RegisterP $end
$var wire 1 0 EN $end
$var wire 1 # clk $end
$var wire 1 & rst $end
$var reg 3 R cuenta [2:0] $end
$var reg 3 S next_state [2:0] $end
$var reg 3 T state [2:0] $end
$upscope $end
$scope module RegisterQ $end
$var wire 1 8 D $end
$var wire 8 U DP [7:0] $end
$var wire 1 B EN $end
$var wire 1 D LS $end
$var wire 1 # clk $end
$var wire 1 & rst $end
$var reg 8 V next_state [7:0] $end
$var reg 8 W outParalela [7:0] $end
$var reg 1 6 outSerie $end
$var reg 8 X state [7:0] $end
$upscope $end
$scope module sum $end
$var wire 8 Y A [7:0] $end
$var wire 8 Z B [7:0] $end
$var wire 1 7 Cin $end
$var reg 1 ? Cout $end
$var reg 8 [ S [7:0] $end
$upscope $end
$upscope $end
$scope module FSM $end
$var wire 1 # clk $end
$var wire 1 # pulso $end
$var wire 1 & rst $end
$var wire 1 ' zero $end
$var reg 3 \ next_state [2:0] $end
$var reg 3 ] salida [2:0] $end
$var reg 3 ^ state [2:0] $end
$upscope $end
$upscope $end
$upscope $end
$scope module testbench $end
$scope module Estados $end
$scope module DUT $end
$scope module RegisterA $end
$upscope $end
$scope module RegisterB $end
$upscope $end
$scope module RegisterC $end
$upscope $end
$scope module RegisterP $end
$upscope $end
$scope module RegisterQ $end
$upscope $end
$scope module sum $end
$upscope $end
$upscope $end
$scope module FSM $end
$upscope $end
$upscope $end
$upscope $end
$enddefinitions $end
#0
$dumpvars
bx ^
bx ]
b0 \
bx [
bx Z
bx Y
bx X
bx W
bx V
b10011 U
bx T
bx S
bx R
xQ
xP
0O
bx N
bx M
bx L
b10111 K
bx J
bx I
bx H
bx G
bx F
bx E
xD
xC
xB
xA
x@
x?
bx >
bx =
bx <
x;
bx :
bx 9
x8
x7
x6
b10011 5
b10111 4
bx 3
x2
x1
x0
x/
bx .
x-
bx ,
bx +
x*
b10011 )
b10111 (
0'
0&
b10011 %
b10111 $
0#
bx "
bx !
$end
#5000
0@
0A
1C
b10111 L
0D
0B
00
0/
02
11
b0 !
b0 3
b0 +
b0 ]
b10 \
b0 ^
1&
1#
#10000
b1 \
0#
#15000
0C
1@
1D
1/
01
b10 !
b10 3
b10111 9
b10111 M
b10111 Z
b10 +
b10 ]
b10111 N
b10 ^
b1 \
1#
#20000
0#
#25000
0@
0P
1C
1B
1A
0/
12
b1 !
b1 3
b1 +
b1 ]
b11 \
b1 ^
1#
#30000
0#
#35000
0B
0A
0*
b0xxxxxxxxxxxxxxxx "
b0xxxxxxxxxxxxxxxx .
b0xxxxxxxxxxxxxxxx F
10
02
b11 !
b11 3
0;
07
b11 +
b11 ]
b0 \
0Q
b11 ^
1#
#40000
0#
#45000
b10011 V
0D
1B
00
11
b0 !
b0 3
b0 +
b0 ]
b10 \
b0 ^
1#
#50000
b1 \
0#
#55000
0C
1@
0B
1D
1-
b0xxxxxxxx00010011 "
b0xxxxxxxx00010011 .
b0xxxxxxxx00010011 F
1/
01
b10 !
b10 3
b10011 :
b10011 W
16
b10 +
b10 ]
b10011 X
b10 ^
b1 \
1#
#60000
0#
#65000
bx0001001 V
0@
1C
1B
1A
0/
12
b1 !
b1 3
b1 +
b1 ]
b11 \
b1 ^
1#
#70000
0#
#75000
0B
0A
b0xxxxxxxxx0001001 "
b0xxxxxxxxx0001001 .
b0xxxxxxxxx0001001 F
10
02
b11 !
b11 3
bx0001001 :
bx0001001 W
bx0001001 V
b11 +
b11 ]
b0 \
bx0001001 X
b11 ^
1#
#80000
0#
#85000
b10011 V
0D
1B
00
11
b0 !
b0 3
b0 +
b0 ]
b10 \
b0 ^
1#
#90000
b1 \
0#
#95000
0C
1@
0B
1D
b0xxxxxxxx00010011 "
b0xxxxxxxx00010011 .
b0xxxxxxxx00010011 F
1/
01
b10 !
b10 3
b10011 :
b10011 W
b10 +
b10 ]
b10011 X
b10 ^
b1 \
1#
#100000
0#
#105000
bx0001001 V
0@
1C
1B
1A
0/
12
b1 !
b1 3
b1 +
b1 ]
b11 \
b1 ^
1#
#110000
0#
#115000
0B
0A
b0xxxxxxxxx0001001 "
b0xxxxxxxxx0001001 .
b0xxxxxxxxx0001001 F
10
02
b11 !
b11 3
bx0001001 :
bx0001001 W
bx0001001 V
b11 +
b11 ]
b0 \
bx0001001 X
b11 ^
1#
#120000
0#
#125000
b10011 V
0D
1B
00
11
b0 !
b0 3
b0 +
b0 ]
b10 \
b0 ^
1#
#130000
b1 \
0#
#135000
0C
1@
0B
1D
b0xxxxxxxx00010011 "
b0xxxxxxxx00010011 .
b0xxxxxxxx00010011 F
1/
01
b10 !
b10 3
b10011 :
b10011 W
b10 +
b10 ]
b10011 X
b10 ^
b1 \
1#
#140000
0#
#145000
bx0001001 V
0@
1C
1B
1A
0/
12
b1 !
b1 3
b1 +
b1 ]
b11 \
b1 ^
1#
#150000
0#
#155000
0B
0A
b0xxxxxxxxx0001001 "
b0xxxxxxxxx0001001 .
b0xxxxxxxxx0001001 F
10
02
b11 !
b11 3
bx0001001 :
bx0001001 W
bx0001001 V
b11 +
b11 ]
b0 \
bx0001001 X
b11 ^
1#
#160000
0#
#165000
b10011 V
0D
1B
00
11
b0 !
b0 3
b0 +
b0 ]
b10 \
b0 ^
1#
#170000
b1 \
0#
#175000
0C
1@
0B
1D
b0xxxxxxxx00010011 "
b0xxxxxxxx00010011 .
b0xxxxxxxx00010011 F
1/
01
b10 !
b10 3
b10011 :
b10011 W
b10 +
b10 ]
b10011 X
b10 ^
b1 \
1#
#180000
0#
#185000
bx0001001 V
0@
1C
1B
1A
0/
12
b1 !
b1 3
b1 +
b1 ]
b11 \
b1 ^
1#
#190000
0#
#195000
0B
0A
b0xxxxxxxxx0001001 "
b0xxxxxxxxx0001001 .
b0xxxxxxxxx0001001 F
10
02
b11 !
b11 3
bx0001001 :
bx0001001 W
bx0001001 V
b11 +
b11 ]
b0 \
bx0001001 X
b11 ^
1#
#200000
0#
#205000
b10011 V
0D
1B
00
11
b0 !
b0 3
b0 +
b0 ]
b10 \
b0 ^
1#
#210000
b1 \
0#
#215000
0C
1@
0B
1D
b0xxxxxxxx00010011 "
b0xxxxxxxx00010011 .
b0xxxxxxxx00010011 F
1/
01
b10 !
b10 3
b10011 :
b10011 W
b10 +
b10 ]
b10011 X
b10 ^
b1 \
1#
#220000
0#
#225000
bx0001001 V
0@
1C
1B
1A
0/
12
b1 !
b1 3
b1 +
b1 ]
b11 \
b1 ^
1#
#230000
0#
#235000
0B
0A
b0xxxxxxxxx0001001 "
b0xxxxxxxxx0001001 .
b0xxxxxxxxx0001001 F
10
02
b11 !
b11 3
bx0001001 :
bx0001001 W
bx0001001 V
b11 +
b11 ]
b0 \
bx0001001 X
b11 ^
1#
#240000
0#
#245000
b10011 V
0D
1B
00
11
b0 !
b0 3
b0 +
b0 ]
b10 \
b0 ^
1#
#250000
b1 \
0#
#255000
0C
1@
0B
1D
b0xxxxxxxx00010011 "
b0xxxxxxxx00010011 .
b0xxxxxxxx00010011 F
1/
01
b10 !
b10 3
b10011 :
b10011 W
b10 +
b10 ]
b10011 X
b10 ^
b1 \
1#
#260000
0#
#265000
bx0001001 V
0@
1C
1B
1A
0/
12
b1 !
b1 3
b1 +
b1 ]
b11 \
b1 ^
1#
#270000
0#
#275000
0B
0A
b0xxxxxxxxx0001001 "
b0xxxxxxxxx0001001 .
b0xxxxxxxxx0001001 F
10
02
b11 !
b11 3
bx0001001 :
bx0001001 W
bx0001001 V
b11 +
b11 ]
b0 \
bx0001001 X
b11 ^
1#
#280000
0#
#285000
b10011 V
0D
1B
00
11
b0 !
b0 3
b0 +
b0 ]
b10 \
b0 ^
1#
#290000
b1 \
0#
#295000
0C
1@
0B
1D
b0xxxxxxxx00010011 "
b0xxxxxxxx00010011 .
b0xxxxxxxx00010011 F
1/
01
b10 !
b10 3
b10011 :
b10011 W
b10 +
b10 ]
b10011 X
b10 ^
b1 \
1#
#300000
0#
#305000
bx0001001 V
0@
1C
1B
1A
0/
12
b1 !
b1 3
b1 +
b1 ]
b11 \
b1 ^
1#
#310000
0#
#315000
0B
0A
b0xxxxxxxxx0001001 "
b0xxxxxxxxx0001001 .
b0xxxxxxxxx0001001 F
10
02
b11 !
b11 3
bx0001001 :
bx0001001 W
bx0001001 V
b11 +
b11 ]
b0 \
bx0001001 X
b11 ^
1#
#320000
0#
#325000
b10011 V
0D
1B
00
11
b0 !
b0 3
b0 +
b0 ]
b10 \
b0 ^
1#
#330000
b1 \
0#
#335000
0C
1@
0B
1D
b0xxxxxxxx00010011 "
b0xxxxxxxx00010011 .
b0xxxxxxxx00010011 F
1/
01
b10 !
b10 3
b10011 :
b10011 W
b10 +
b10 ]
b10011 X
b10 ^
b1 \
1#
#340000
0#
#345000
bx0001001 V
0@
1C
1B
1A
0/
12
b1 !
b1 3
b1 +
b1 ]
b11 \
b1 ^
1#
#350000
0#
#355000
0B
0A
b0xxxxxxxxx0001001 "
b0xxxxxxxxx0001001 .
b0xxxxxxxxx0001001 F
10
02
b11 !
b11 3
bx0001001 :
bx0001001 W
bx0001001 V
b11 +
b11 ]
b0 \
bx0001001 X
b11 ^
1#
#360000
0#
#365000
b10011 V
0D
1B
00
11
b0 !
b0 3
b0 +
b0 ]
b10 \
b0 ^
1#
#370000
b1 \
0#
#375000
0C
1@
0B
1D
b0xxxxxxxx00010011 "
b0xxxxxxxx00010011 .
b0xxxxxxxx00010011 F
1/
01
b10 !
b10 3
b10011 :
b10011 W
b10 +
b10 ]
b10011 X
b10 ^
b1 \
1#
#380000
0#
#385000
bx0001001 V
0@
1C
1B
1A
0/
12
b1 !
b1 3
b1 +
b1 ]
b11 \
b1 ^
1#
#390000
0#
#395000
0B
0A
b0xxxxxxxxx0001001 "
b0xxxxxxxxx0001001 .
b0xxxxxxxxx0001001 F
10
02
b11 !
b11 3
bx0001001 :
bx0001001 W
bx0001001 V
b11 +
b11 ]
b0 \
bx0001001 X
b11 ^
1#
#400000
0#
#405000
b10011 V
0D
1B
00
11
b0 !
b0 3
b0 +
b0 ]
b10 \
b0 ^
1#
#410000
b1 \
0#
#415000
0C
1@
0B
1D
b0xxxxxxxx00010011 "
b0xxxxxxxx00010011 .
b0xxxxxxxx00010011 F
1/
01
b10 !
b10 3
b10011 :
b10011 W
b10 +
b10 ]
b10011 X
b10 ^
b1 \
1#
#420000
0#
#425000
bx0001001 V
0@
1C
1B
1A
0/
12
b1 !
b1 3
b1 +
b1 ]
b11 \
b1 ^
1#
#430000
0#
#435000
0B
0A
b0xxxxxxxxx0001001 "
b0xxxxxxxxx0001001 .
b0xxxxxxxxx0001001 F
10
02
b11 !
b11 3
bx0001001 :
bx0001001 W
bx0001001 V
b11 +
b11 ]
b0 \
bx0001001 X
b11 ^
1#
#440000
0#
#445000
b10011 V
0D
1B
00
11
b0 !
b0 3
b0 +
b0 ]
b10 \
b0 ^
1#
#450000
b1 \
0#
#455000
0C
1@
0B
1D
b0xxxxxxxx00010011 "
b0xxxxxxxx00010011 .
b0xxxxxxxx00010011 F
1/
01
b10 !
b10 3
b10011 :
b10011 W
b10 +
b10 ]
b10011 X
b10 ^
b1 \
1#
#460000
0#
#465000
bx0001001 V
0@
1C
1B
1A
0/
12
b1 !
b1 3
b1 +
b1 ]
b11 \
b1 ^
1#
#470000
0#
#475000
0B
0A
b0xxxxxxxxx0001001 "
b0xxxxxxxxx0001001 .
b0xxxxxxxxx0001001 F
10
02
b11 !
b11 3
bx0001001 :
bx0001001 W
bx0001001 V
b11 +
b11 ]
b0 \
bx0001001 X
b11 ^
1#
#480000
0#
#485000
b10011 V
0D
1B
00
11
b0 !
b0 3
b0 +
b0 ]
b10 \
b0 ^
1#
#490000
b1 \
0#
#495000
0C
1@
0B
1D
b0xxxxxxxx00010011 "
b0xxxxxxxx00010011 .
b0xxxxxxxx00010011 F
1/
01
b10 !
b10 3
b10011 :
b10011 W
b10 +
b10 ]
b10011 X
b10 ^
b1 \
1#
#500000
0#
#505000
bx0001001 V
0@
1C
1B
1A
0/
12
b1 !
b1 3
b1 +
b1 ]
b11 \
b1 ^
1#
