Basic_course_modules/Muxes/src/design.sv
// Code your design here


//===================== Mux 2 a 1 =======================//

`timescale 1ns/1ps

module mux(
  	input D0, D1, S,
  	output Q
);
  
//Otra opción
//module mux(D0,D1,S,Q);
//  input D0,D1,S;
//  output Q;
  
  
  wire Snegado;
  wire n0, n1;
  
  //A nivel de compuertas
  //Tipo nombre (out, in)
  not u0 (Snegado, S);
  and u1 (n0, D0,Snegado);
  and u2 (n1, D1,S);
  or u3 (Q, n0,n1);
  
  //Con la expresión booleana
  //assign Q = (D0&(~S)) | (D1&S);
  
  //Con asignación más alto nivel
  //Assign varSal = expr ? true : false;
  //assign Q = S?D1:D0;

  //Paso a paso
  //assign Snegado = ~S;
  //assign n0 = D0&Snegado;
  //assign n1 = D1&S;
  //assign Q = n0|n1;

  //Always
  //Ejecútese cada vez que haya un cambio en D0, D1 o S
  //always @ (D0 or D1 or S) begin
  // * cada vez que cualquiera de todos cambie
  
  //reg Q;
  //always @ (*) begin
    //Var a la izq => var de salida => reg
    //Q = (D0&(~S)) | (D1&S);
  //end
  
  //Mejor usar always para instrucciones de más alto nivel
  //always @ (*) begin
    //if (!S): Q = D0;
    //else Q = D1;
  //end
  
  
  //O con case
  //always @ (*) begin
    //case(S)
      //0: Q = D0;
      //1: Q = D1;
    //endcase
  //end
  
  
endmodule


//===================== Mux 4 a 1 =======================//

`timescale 1ns/1ps

//Forma estructural
/*module mux4a1( input D0, D1, D2, D3, S0, S1, output Q);
  
  wire n0, n1;
  mux m1 (.D0(D0), .D1(D1), .S(S0), .Q(n0));
  mux m2 (.D0(D2), .D1(D3), .S(S0), .Q(n1));
  mux m3 (.D0(n0), .D1(n1), .S(S1), .Q(Q));
  
endmodule*/

//Otra forma de más alto nivel
/*module mux4a1( input D0, D1, D2, D3, S0, S1, output reg Q); //Ojo al reg
  
  always @ (*) begin
    //Concatenar S1 y S0
    case({S1,S0})
      2'b00: Q = D0;
      2'b01: Q = D1;
      2'b10: Q = D2;
      2'b11: Q = D3;
    endcase
  end
  
endmodule*/


//Otra forma de dos bits
module mux4a1(input D0, D1, D2, D3, input[1:0] S, output Q);
  
  wire n0, n1;
  mux m1 (.D0(D0), .D1(D1), .S(S[0]), .Q(n0));
  mux m2 (.D0(D2), .D1(D3), .S(S[0]), .Q(n1));
  mux m3 (.D0(n0), .D1(n1), .S(S[1]), .Q(Q));
  
endmodule



//===================== Mux 4 a 1 Bus =======================//

module mux4a1bus(input [3:0] D0, D1, D2, D3, //Ahora cada una es de 4 bits
              	input[1:0] S, 
              	output reg [3:0] Q); //Ojo al reg
  
  always @ (*) begin
    case(S)
      2'b00: Q = D0;
      2'b01: Q = D1;
      2'b10: Q = D2;
      2'b11: Q = D3;
    endcase
  end
  
endmodule


//===================== Mux 4 a 1 Bus =======================//

//#(parameter nombre = valorxDefecto)
module mux4a1BusParam #(parameter ANCHO = 8)
  (input [ANCHO-1:0] D0, D1, D2, D3,
     input[1:0] S, 
     output reg [ANCHO-1:0] Q
  );
  
  always @ (*) begin
    case(S)
      2'b00: Q = D0;
      2'b01: Q = D1;
      2'b10: Q = D2;
      2'b11: Q = D3;
    endcase
  end
  
endmodule


//===================== DeMux 1 a 4 Bus =======================//

module demux1a4Param #(parameter ANCHO = 8)
  	(input [1:0] S,
     input [ANCHO-1:0] D, 
     output reg [ANCHO-1:0] out0, out1, out2, out3
  );
  
  /*always @ (*) begin
    case(S)
      //Error lógico porque guardaría el último valor que tuvo
      //Es combinacional: solo debe depender de las entradas actuales
      //Además no se inicializan por lo que empiezan con X
      0: out0 = D;
      1: out1 = D;
      2: out2 = D;
      3: out3 = D;
    endcase
  end*/
  
  //Manera larga
  /*always @ (*) begin
    case(S)
      0: begin
        out0 = D;
        out1 = 0;
      	out2 = 0;
      	out3 = 0;
      end
      1: begin
        out0 = 0;
        out1 = D;
      	out2 = 0;
      	out3 = 0;
      end
      2: begin
        out0 = 0;
        out1 = 0;
      	out2 = D;
      	out3 = 0;
      end
      3: begin
        out0 = 0;
        out1 = 0;
      	out2 = 0;
      	out3 = D;
      end
    endcase
  end*/
  
  //Manera corta
  //Funciona porque se ejecuta cada vez que cambia una variable
  always @ (*) begin
    out0 = 0;
    out1 = 0;
    out2 = 0;
    out3 = 0;
    case(S)
      0: out0 = D;
      1: out1 = D;
      2: out2 = D;
      3: out3 = D;
    endcase
  end
  
endmodule


//===================== Mux 3 a 1 Bus =======================//

module mux3a1BusParam #(parameter ANCHO = 8)
  (input [ANCHO-1:0] D0, D1, D2,
     input[1:0] S, 
     output reg [ANCHO-1:0] Q
  );
  
  /*always @ (*) begin
    //Como no se tiene caso para 11 (3), se guarda el último valor
    //Se crea memoria! => error lógico
    case(S)
      2'b00: Q = D0;
      2'b01: Q = D1;
      2'b10: Q = D2;
    endcase
  end*/
  
  always @ (*) begin
    //Q = 0;  una opción
    case(S)
      2'b00: Q = D0;
      2'b01: Q = D1;
      2'b10: Q = D2;
      default: Q = 0; //Otra solución
      //2'b10: Q = 0;  Otra solución, larga si hay que poner muchos
    endcase
  end
  
  //======= Con if else
  /*always @ (*) begin
    if(S==0) Q=D0;
    else if (S==1) Q=D1;
    else if (S==2) Q=D2;

    //Mismo error se generaría si no se pusiera el else
    else Q=0;
  end*/
  
endmodule

Basic_course_modules/Muxes/tb/testbench.sv
// Code your testbench here (pruebas)

`timescale 1ns/1ps

module mux3a1BusParam_tb;
 
  parameter ANCHO = 16;
  reg [1:0] seleccion;
  reg [ANCHO-1:0] dato0_p, dato1_p, dato2_p; 
  wire [ANCHO-1:0] salida_p;
  
  mux3a1BusParam #(.ANCHO(ANCHO)) DUT_MUX (.S(seleccion),
                                           .D0(dato0_p), 
                                           .D1(dato1_p),
                                           .D2(dato2_p),
                                           .Q(salida_p)
  );
  
  initial begin
    $dumpfile("mux3a1BusParam_tb.vcd");
    $dumpvars(0,mux3a1BusParam_tb);
  end
  
  //Para inicializar variables y valores
  initial begin
    seleccion = 0;
    dato0_p = $random;
    dato1_p = $random;
    dato2_p = $random;   
    repeat(8) begin
      repeat(3) begin
        #5
        dato0_p = $random;
    	dato1_p = $random;
    	dato2_p = $random;
      end
      #5
      seleccion = seleccion+1;
    end
    #5
    $finish;
    
  end
endmodule

Basic_course_modules/Muxes/tb/mux3a1BusParam_tb.vcd
$date
	Wed Jan  3 15:38:15 2024
$end
$version
	Icarus Verilog
$end
$timescale
	1ps
$end
$scope module mux3a1BusParam_tb $end
$var wire 16 ! salida_p [15:0] $end
$var reg 16 " dato0_p [15:0] $end
$var reg 16 # dato1_p [15:0] $end
$var reg 16 $ dato2_p [15:0] $end
$var reg 2 % seleccion [1:0] $end
$scope module DUT_MUX $end
$var wire 16 & D0 [15:0] $end
$var wire 16 ' D1 [15:0] $end
$var wire 16 ( D2 [15:0] $end
$var wire 2 ) S [1:0] $end
$var reg 16 * Q [15:0] $end
$upscope $end
$upscope $end
$enddefinitions $end
#0
$dumpvars
b11010100100100 *
b0 )
b1101011000001001 (
b101111010000001 '
b11010100100100 &
b0 %
b1101011000001001 $
b101111010000001 #
b11010100100100 "
b11010100100100 !
$end
#5000
b101011001100011 !
b101011001100011 *
b1001100110001101 $
b1001100110001101 (
b111101100001101 #
b111101100001101 '
b101011001100011 "
b101011001100011 &
#10000
b1000010001100101 !
b1000010001100101 *
b1110001100000001 $
b1110001100000001 (
b101001000010010 #
b101001000010010 '
b1000010001100101 "
b1000010001100101 &
#15000
b1100110100001101 !
b1100110100001101 *
b1100110100111101 $
b1100110100111101 (
b1111000101110110 #
b1111000101110110 '
b1100110100001101 "
b1100110100001101 &
#20000
b1111000101110110 !
b1111000101110110 *
b1 %
b1 )
#25000
b1111011110001100 !
b1111011110001100 *
b1110100111111001 $
b1110100111111001 (
b1111011110001100 #
b1111011110001100 '
b101011111101101 "
b101011111101101 &
#30000
b1000010011000101 !
b1000010011000101 *
b1101001010101010 $
b1101001010101010 (
b1000010011000101 #
b1000010011000101 '
b10010011000110 "
b10010011000110 &
#35000
b111001001110111 !
b111001001110111 *
b1101011000010010 $
b1101011000010010 (
b111001001110111 #
b111001001110111 '
b1111011111100101 "
b1111011111100101 &
#40000
b1101011000010010 !
b1101011000010010 *
b10 %
b10 )
#45000
b1001011011001110 !
b1001011011001110 *
b1001011011001110 $
b1001011011001110 (
b110100111110010 #
b110100111110010 '
b1101101110001111 "
b1101101110001111 &
#50000
b100100101011100 !
b100100101011100 *
b100100101011100 $
b100100101011100 (
b100111011000101 #
b100111011000101 '
b111101011101000 "
b111101011101000 &
#55000
b10011001100101 !
b10011001100101 *
b10011001100101 $
b10011001100101 (
b101100000101101 #
b101100000101101 '
b10100010111101 "
b10100010111101 &
#60000
b0 !
b0 *
b11 %
b11 )
#65000
b10001010000000 $
b10001010000000 (
b1000011100001010 #
b1000011100001010 '
b110001001100011 "
b110001001100011 &
#70000
b1100110010011101 $
b1100110010011101 (
b100010110101010 #
b100010110101010 '
b10000100100000 "
b10000100100000 &
#75000
b11100000001101 $
b11100000001101 (
b1011100000010011 #
b1011100000010011 '
b11111010010110 "
b11111010010110 &
#80000
b11111010010110 !
b11111010010110 *
b0 %
b0 )
#85000
b1101011001010011 !
b1101011001010011 *
b10101011010101 $
b10101011010101 (
b1101110101101011 #
b1101110101101011 '
b1101011001010011 "
b1101011001010011 &
#90000
b100101000000010 !
b100101000000010 *
b1110100100011101 $
b1110100100011101 (
b11111010101110 #
b11111010101110 '
b100101000000010 "
b100101000000010 &
#95000
b111001011001111 !
b111001011001111 *
b110010100001010 $
b110010100001010 (
b100100100100011 #
b100100100100011 '
b111001011001111 "
b111001011001111 &
#100000
b100100100100011 !
b100100100100011 *
b1 %
b1 )
#105000
b100110000111100 !
b100110000111100 *
b1011110111110010 $
b1011110111110010 (
b100110000111100 #
b100110000111100 '
b101011001010 "
b101011001010 &
#110000
b1011001101000001 !
b1011001101000001 *
b11010011011000 $
b11010011011000 (
b1011001101000001 #
b1011001101000001 '
b110000110001010 "
b110000110001010 &
#115000
b1001010001001 !
b1001010001001 *
b110111101011 $
b110111101011 (
b1001010001001 #
b1001010001001 '
b1111001101111000 "
b1111001101111000 &
#120000
b110111101011 !
b110111101011 *
b10 %
b10 )
#125000
b1001110101110 !
b1001110101110 *
b1001110101110 $
b1001110101110 (
b1111100111000110 #
b1111100111000110 '
b110010110110110 "
b110010110110110 &
#130000
b1001101000001011 !
b1001101000001011 *
b1001101000001011 $
b1001101000001011 (
b1101110100101010 #
b1101110100101010 '
b1010111100 "
b1010111100 &
#135000
b101010101001111 !
b101010101001111 *
b101010101001111 $
b101010101001111 (
b100000110000101 #
b100000110000101 '
b1011111001110001 "
b1011111001110001 &
#140000
b0 !
b0 *
b11 %
b11 )
#145000
b11001001111110 $
b11001001111110 (
b11001100111010 #
b11001100111010 '
b110000000111011 "
b110000000111011 &
#150000
b100101111011001 $
b100101111011001 (
b1001101111110001 #
b1001101111110001 '
b100101100010101 "
b100101100010101 &
#155000
b101010110011111 $
b101010110011111 (
b1111101101001100 #
b1111101101001100 '
b11101100010 "
b11101100010 &
#160000
b11101100010 !
b11101100010 *
b0 %
b0 )
